.gitignore
LICENSE.txt
MANIFEST.in
README.md
changes.txt
description.md
setup.cfg
setup.py
data/tcremoval/tcparameters.txt
figs/download_continuous_example.png
figs/noise_xcorr_example.png
figs/seisgo_logo.png
notebooks/OBS_orientation_Cascadia.csv
notebooks/download_catalog.ipynb
notebooks/download_continuous.ipynb
notebooks/seisgo_download_xcorr_demo.ipynb
notebooks/seisgo_dvv_workflow_example.ipynb
notebooks/seisgo_xcorr_sac.ipynb
notebooks/tcremoval_continuous.ipynb
notebooks/tcremoval_continuous_correctorientation.ipynb
notebooks/tcremoval_continuous_local.ipynb
notebooks/tcremoval_earthquakes.ipynb
notebooks/.ipynb_checkpoints/seisgo_download_xcorr_demo-checkpoint.ipynb
notebooks/embededfigs/JaniszewskiGJI2019Fig5.png
scripts/.DS_Store
scripts/EQDownload.py
scripts/OBS_orientation_Cascadia.csv
scripts/seisgo_BANX_azimuthal_anisotropy.py
scripts/seisgo_ccf2sac_MPI.py
scripts/seisgo_cleaning_MPI.py
scripts/seisgo_download_MPI.py
scripts/seisgo_download_obsdata.py
scripts/seisgo_stacking_MPI.py
scripts/seisgo_tcremoval_continuous.py
scripts/seisgo_tcremoval_continuous_MPI.py
scripts/seisgo_xcorr_sac.py
scripts/ExtractEGFsFromNoise/.DS_Store
scripts/ExtractEGFsFromNoise/1_download_MPI.py
scripts/ExtractEGFsFromNoise/2_xcorr_MPI.py
scripts/ExtractEGFsFromNoise/3_merge_pairs_bysources_MPI.py
scripts/ExtractEGFsFromNoise/4_split_sides_bysources_MPI.py
scripts/ExtractEGFsFromNoise/README.md
scripts/ExtractEGFsFromNoise/submit_download.sh
scripts/ExtractEGFsFromNoise/submit_merge_pairs_bysources_MPI.sh
scripts/ExtractEGFsFromNoise/submit_split_sides.sh
scripts/ExtractEGFsFromNoise/submit_xcorr_MPI.sh
seisgo/__init__.py
seisgo/anisotropy.py
seisgo/clustering.py
seisgo/dispersion.py
seisgo/downloaders.py
seisgo/helpers.py
seisgo/monitoring.py
seisgo/noise.py
seisgo/obsmaster.py
seisgo/plotting.py
seisgo/simulation.py
seisgo/stacking.py
seisgo/types.py
seisgo/utils.py
seisgo.egg-info/PKG-INFO
seisgo.egg-info/SOURCES.txt
seisgo.egg-info/dependency_links.txt
seisgo.egg-info/requires.txt
seisgo.egg-info/top_level.txt
seisgo/__pycache__/__init__.cpython-37.pyc
seisgo/__pycache__/obsmaster.cpython-37.pyc
