Metadata-Version: 2.1
Name: seisgo
Version: 1.0.0
Summary: A ready-to-go Python toolbox for seismic data analysis
Home-page: https://github.com/xtyangpsp/SeisGo
Download-URL: https://github.com/xtyangpsp/SeisGo/archive/refs/tags/v1.0.0.tar.gz
Author: Xiaotao Yang
Author-email: stcyang@gmail.com
Maintainer: Xiaotao Yang
Maintainer-email: stcyang@gmail.com
License: MIT license
Keywords: seismology,seismic data analysis,seismic toolbox
Classifier: Development Status :: 4 - Beta
Classifier: License :: OSI Approved :: MIT License
Classifier: Programming Language :: Python :: 3.7
Requires-Python: >=3.6
License-File: LICENSE.txt
Requires-Dist: numpy
Requires-Dist: scipy
Requires-Dist: pandas
Requires-Dist: obspy
Requires-Dist: pyasdf
Requires-Dist: numba
Requires-Dist: pycwt
Requires-Dist: shapely
Requires-Dist: netCDF4
Requires-Dist: tslearn
Requires-Dist: plotly
Requires-Dist: kaleido
Requires-Dist: minisom
Requires-Dist: stockwell
Requires-Dist: kneed
Requires-Dist: utm
